tulpar/__init__.py
tulpar/base_decorator.py
tulpar/config.py
tulpar/middleware.py
tulpar/model.py
tulpar/page.py
tulpar/protocols/hook.py
tulpar/protocols/page.py
tulpar/protocols/resource.py
tulpar/resource.py
tulpar/tulpar.py
tulpar-0.0.3.dist-info/LICENSE
tulpar-0.0.3.dist-info/WHEEL
tulpar-0.0.3.dist-info/METADATA
tulpar-0.0.3.dist-info/RECORD
